ledidi/__init__.py
ledidi/ledidi.py
ledidi/losses.py
ledidi/plot.py
ledidi/pruning.py
ledidi/wrappers.py
ledidi-2.1.0.dist-info/licenses/LICENSE
ledidi-2.1.0.dist-info/METADATA
ledidi-2.1.0.dist-info/WHEEL
ledidi-2.1.0.dist-info/top_level.txt
ledidi-2.1.0.dist-info/RECORD
